{
  "type": "Feature",
  "geometry": {
    "type": "Point",
    "coordinates": [-70.7565459, -33.440753]
  },
  "properties": {
    "name": "Casa Aldea, Sánguches",
    "description": "Hamburguesas, sámguches"
  }
}
