{
  "type": "FeatureCollection",
  "features": [
    {
      "type": "Feature",
      "geometry": {
        "type": "Point",
        "coordinates": [-70.756545, -33.44075   ]
      },
      "properties": {
        "name": "Casa Aldea",
        "description": "Sargento aldea 970 - Pudahuel, Hamburguesas, sánguches"
      }
    },
    {
      "type": "Feature",
      "geometry": {
        "type": "Point",
        "coordinates": [-70.5581585, -33.3921212 ]
      },
      "properties": {
        "name": "Franklin Klunssen",
        "description": "Fernando de Arguello 7430 - Vitacura, Hamburguesas, sánguches"
      }
    },
    {
      "type": "Feature",
      "geometry": {
        "type": "Point",
        "coordinates": [-70.671492, -33.4086552 ]
      },
      "properties": {
        "name": "El Lobito ",
        "description": "Nueva de Matte 2585 - Independencia, Hamburguesas, sánguches"
      }
    }



  ]
}
